xml_diff/__init__.py
xml_diff/__main__.py
xml_diff-0.7.1.dist-info/licenses/LICENSE
xml_diff-0.7.1.dist-info/METADATA
xml_diff-0.7.1.dist-info/WHEEL
xml_diff-0.7.1.dist-info/top_level.txt
xml_diff-0.7.1.dist-info/RECORD
