Metadata-Version: 2.4
Name: xml_diff
Version: 0.7.1
Summary: Compares two XML documents by diffing their text, ignoring structure, and wraps changed text in <del>/<ins> tags.
Home-page: https://github.com/joshdata/xml_diff
Author: Joshua Tauberer
Author-email: jt@occams.info
License: Unlicense
Keywords: compare diff XML
License-File: LICENSE
Requires-Dist: lxml
Dynamic: author
Dynamic: author-email
Dynamic: description
Dynamic: description-content-type
Dynamic: home-page
Dynamic: keywords
Dynamic: license
Dynamic: license-file
Dynamic: requires-dist
Dynamic: summary
